carboncue_cli/__init__.py
carboncue_cli/main.py
carboncue_cli-1.1.0.dist-info/METADATA
carboncue_cli-1.1.0.dist-info/WHEEL
carboncue_cli-1.1.0.dist-info/entry_points.txt
carboncue_cli-1.1.0.dist-info/RECORD
