Metadata-Version: 2.4
Name: carboncue-cli
Version: 1.1.0
Summary: Terminal interface for carbon-aware development
License: MIT
Requires-Python: >=3.11
Requires-Dist: carboncue-sdk>=1.1.0
Requires-Dist: click>=8.1.8
Requires-Dist: python-dotenv>=1.0.1
Requires-Dist: rich>=13.9.4
Provides-Extra: dev
Requires-Dist: pytest-asyncio>=0.25.2; extra == 'dev'
Requires-Dist: pytest>=8.3.4; extra == 'dev'
